pyfix/__init__.py
pyfix/core.py
pyfix/errors.yaml
pyfix_cli-0.1.1.dist-info/licenses/LICENSE
pyfix_cli-0.1.1.dist-info/METADATA
pyfix_cli-0.1.1.dist-info/WHEEL
pyfix_cli-0.1.1.dist-info/top_level.txt
pyfix_cli-0.1.1.dist-info/RECORD
