Metadata-Version: 2.4
Name: pyfix-cli
Version: 0.1.1
Summary: Объясняет Python-ошибки на русском — как друг
Home-page: https://github.com/thepyfix/pyfix
Author: SAS
Author-email: pyfixhelp@gmail.com
License: MIT
Classifier: Programming Language :: Python :: 3
Classifier: Operating System :: OS Independent
Requires-Python: >=3.8
License-File: LICENSE
Requires-Dist: PyYAML
Dynamic: author
Dynamic: author-email
Dynamic: classifier
Dynamic: description
Dynamic: description-content-type
Dynamic: home-page
Dynamic: license
Dynamic: license-file
Dynamic: requires-dist
Dynamic: requires-python
Dynamic: summary
